ctpaperclip/README.MD
ctpaperclip/__init__.py
ctpaperclip/requirements.txt
ctpaperclip/thirdparty.json
ctpaperclip-0.10.dist-info/LICENSE.rst
ctpaperclip-0.10.dist-info/METADATA
ctpaperclip-0.10.dist-info/WHEEL
ctpaperclip-0.10.dist-info/top_level.txt
ctpaperclip-0.10.dist-info/RECORD
