Metadata-Version: 2.1
Name: ctpaperclip
Version: 0.10
Summary: Clipboard - Write/Read - supports Images, UTF-8, bytes, file lists, and more! (Windows only)
Home-page: https://github.com/hansalemaos/ctpaperclip
Author: Johannes Fischer
Author-email: aulasparticularesdealemaosp@gmail.com
License: MIT
Keywords: clipboard,ctypes,pypaperclip,copy,paste
Classifier: Development Status :: 4 - Beta
Classifier: Programming Language :: Python :: 3 :: Only
Classifier: Programming Language :: Python :: 3.10
Classifier: Topic :: Software Development :: Libraries :: Python Modules
Classifier: Topic :: Utilities
License-File: LICENSE.rst
Requires-Dist: Pillow
Requires-Dist: ctypes-window-info
Requires-Dist: deepcopyall
Requires-Dist: kthread
Requires-Dist: kthread-sleep
Requires-Dist: mousekey
Requires-Dist: numpy
Requires-Dist: tolerant-isinstance
